{
  "name": "Moonlight (Material)",
  "dark": true,
  "author": "Mallowigi",
  "editorScheme": "/colors/Moonlight.xml",
  "ui": {},
  "icons": {
    "ColorPalette": {
      "#43494A": "#191a2a",
      "#6B6B6B": "#a9b8e8",
      "#A7A7A7": "#222436",
      "#3D6185": "#4fd6be",
      "#466D94": "#4fd6be",
      "#3C3F41": "#222436",
      "#545556": "#828bb8",
      "#606060": "#828bb8",
      "#9AA7B0": "#c8d3f5",
      "#675133": "#4fd6be",
      "Actions.Blue": "#82aaff",
      "Actions.Green": "#c3e88d",
      "Actions.Grey": "#a9b8e8",
      "Actions.GreyInline": "#7a88cf",
      "Actions.GreyInline.Dark": "#c8d3f5",
      "Actions.Red": "#ff757f",
      "Actions.Yellow": "#c099ff",
      "Checkbox.Background.Default": "#191a2a",
      "Checkbox.Background.Default.Dark": "#191a2a",
      "Checkbox.Background.Disabled": "#2f334d",
      "Checkbox.Background.Disabled.Dark": "#2f334d",
      "Checkbox.Border.Default": "#222436",
      "Checkbox.Border.Default.Dark": "#222436",
      "Checkbox.Border.Disabled": "#828bb8",
      "Checkbox.Border.Disabled.Dark": "#828bb8",
      "Checkbox.Focus.Thin.Default": "#4fd6be",
      "Checkbox.Focus.Thin.Default.Dark": "#4fd6be",
      "Checkbox.Focus.Wide": "#4fd6be",
      "Checkbox.Focus.Wide.Dark": "#4fd6be",
      "Checkbox.Foreground.Disabled": "#828bb8",
      "Checkbox.Foreground.Disabled.Dark": "#828bb8",
      "Checkbox.Background.Selected": "#4fd6be",
      "Checkbox.Background.Selected.Dark": "#222436",
      "Checkbox.Border.Selected": "#4fd6be",
      "Checkbox.Border.Selected.Dark": "#4fd6be",
      "Checkbox.Foreground.Selected": "#4fd6be",
      "Checkbox.Foreground.Selected.Dark": "#4fd6be",
      "Checkbox.Focus.Thin.Selected": "#c8d3f5",
      "Checkbox.Focus.Thin.Selected.Dark": "#c8d3f5",
      "Objects.Grey": "#7a88cf",
      "Objects.Blue": "#82aaff",
      "Objects.RedStatus": "#ff757f",
      "Objects.Red": "#ff757f",
      "Objects.Pink": "#c099ff",
      "Objects.Yellow": "#c099ff",
      "Objects.Green": "#c3e88d",
      "Objects.Purple": "#c099ff",
      "Objects.BlackText": "#c8d3f5",
      "Objects.YellowDark": "#ff966c",
      "Objects.GreenAndroid": "#c3e88d"
    }
  }
}